Metadata-Version: 2.3
Name: just-semantic-search-scholar
Version: 2.5.0
Summary: Core interfaces for hybrid search implementations (CUDA version)
License: Apache-2.0
Keywords: python,llm,gpu,cuda,science,review,hybrid search,semantic search,cpu
Author: Anton Kulaga
Author-email: antonkulaga@gmail.com
Requires-Python: >=3.10,<3.15
Classifier: Development Status :: 3 - Alpha
Classifier: Intended Audience :: Developers
Classifier: License :: OSI Approved :: Apache Software License
Classifier: Operating System :: MacOS :: MacOS X
Classifier: Operating System :: Microsoft :: Windows
Classifier: Operating System :: Unix
Classifier: Programming Language :: Python :: 3
Classifier: Programming Language :: Python :: 3.10
Classifier: Programming Language :: Python :: 3.11
Classifier: Programming Language :: Python :: 3.12
Classifier: Programming Language :: Python :: 3.13
Requires-Dist: just-semantic-search-meili-cuda
Requires-Dist: patito (>=0.8.3)
Requires-Dist: polars (>=1.20.0)
Requires-Dist: pyfunctional (>=1.5.0)
Requires-Dist: seaborn (>=0.13.2)
Requires-Dist: semanticscholar (>=0.10.0)
Requires-Dist: typer (>=0.9.0)
